new_face/__init__.py
new_face/kernel/__init__.py
new_face/kernel/alignment.py
new_face/kernel/detection.py
new_face/kernel/landmark.py
new_face/kernel/lbpcnn.py
new_face/kernel/lbph.py
new_face/kernel/openface.py
new_face/tools/__init__.py
new_face/tools/config.py
new_face/tools/download.py
new_face/tools/models.py
new_face-0.0.4.6.dist-info/LICENSE
new_face-0.0.4.6.dist-info/METADATA
new_face-0.0.4.6.dist-info/WHEEL
new_face-0.0.4.6.dist-info/top_level.txt
new_face-0.0.4.6.dist-info/RECORD
