Metadata-Version: 2.1
Name: new-face
Version: 0.0.4.6
Summary: Face Recognition Tools
Home-page: https://github.com/Michael07220823/new_face.git
Author: Overcomer
Author-email: michael31703@gmail.com
License: MIT License
Keywords: Face Recognition
Platform: UNKNOWN
Classifier: Operating System :: Microsoft :: Windows
Classifier: Programming Language :: Python :: 3.6
Classifier: Programming Language :: Python :: 3.7
Classifier: Programming Language :: Python :: 3.8
Classifier: Programming Language :: Python :: 3.9
Classifier: License :: OSI Approved :: MIT License
License-File: LICENSE
Requires-Dist: tensorflow (>=2.0.0)
Requires-Dist: scikit-learn (==1.0.1)
Requires-Dist: sklearn
Requires-Dist: mtcnn
Requires-Dist: imutils
Requires-Dist: cmake
Requires-Dist: dlib
Requires-Dist: scikit-image
Requires-Dist: matplotlib
Requires-Dist: opencv-python
Requires-Dist: opencv-contrib-python
Requires-Dist: pydot
Requires-Dist: gdown
Requires-Dist: new-tools
Requires-Dist: new-timer
